Metadata-Version: 2.1
Name: pyaerodynamics
Version: 1.0.0
Summary: Aerodynamic calculation
Home-page: UNKNOWN
Author-email: rvasilikhin@gmail.com
License: UNKNOWN
Platform: UNKNOWN
